xia_storer_gcs/__init__.py
xia_storer_gcs/storer.cpython-311-darwin.so
xia_storer_gcs-0.0.7.dist-info/LICENSE.txt
xia_storer_gcs-0.0.7.dist-info/METADATA
xia_storer_gcs-0.0.7.dist-info/WHEEL
xia_storer_gcs-0.0.7.dist-info/top_level.txt
xia_storer_gcs-0.0.7.dist-info/RECORD
