Metadata-Version: 2.1
Name: xia-storer-gcs
Version: 0.0.7
Summary: UNKNOWN
Home-page: https://develop.x-i-a.com/docs/xia-storer-gcs/0.0.7/index.html
Author: X-I-A
Author-email: admin@x-i-a.com
License: UNKNOWN
Platform: UNKNOWN
Requires-Python: >=3.9
License-File: LICENSE.txt
Requires-Dist: gcsfs
Requires-Dist: google-cloud-storage
Requires-Dist: xia-storer
